{
  "strategy_name": "Divergence_Strategy",
  "last_updated": "2025-10-11T18:09:50.278856",
  "total_symbols_analyzed": 7,
  "signals_generated": 0,
  "analysis_summary": {
    "strong_buy": 0,
    "buy": 0,
    "hold": 0,
    "no_signal": 5
  },
  "signals": {
    "AMZN": {
      "signal_type": "NO_SIGNAL",
      "confidence": 0.0,
      "entry_reason": "No divergence signals detected",
      "timestamp": "2025-10-11T18:09:50.205981",
      "market_condition": "TRENDING_DOWN",
      "volatility_environment": "Medium Volatility",
      "position_size": 0.0,
      "stop_loss": 0.0,
      "profit_target": 0.0,
      "auto_approve": true
    },
    "AAPL": {
      "signal_type": "STRONG_SELL",
      "confidence": 0.9,
      "entry_reason": "Strong bearish divergence detected in technical indicators",
      "timestamp": "2025-10-11T18:09:50.225250",
      "market_condition": "BEARISH_DIVERGENCE",
      "volatility_environment": "Medium Volatility",
      "position_size": 2.0,
      "stop_loss": 252.64946407671263,
      "profit_target": 230.51107184657477,
      "auto_approve": true
    },
    "BAC": {
      "signal_type": "STRONG_SELL",
      "confidence": 0.9,
      "entry_reason": "Strong bearish divergence detected in technical indicators",
      "timestamp": "2025-10-11T18:09:50.228325",
      "market_condition": "BEARISH_DIVERGENCE",
      "volatility_environment": "Medium Volatility",
      "position_size": 2.0,
      "stop_loss": 50.032444415768786,
      "profit_target": 45.88511116846242,
      "auto_approve": true
    },
    "PLTR": {
      "signal_type": "NO_SIGNAL",
      "confidence": 0.0,
      "entry_reason": "No divergence signals detected",
      "timestamp": "2025-10-11T18:09:50.229398",
      "market_condition": "RANGE_BOUND",
      "volatility_environment": "High Volatility",
      "position_size": 0.0,
      "stop_loss": 0.0,
      "profit_target": 0.0,
      "auto_approve": true
    },
    "NVDA": {
      "signal_type": "NO_SIGNAL",
      "confidence": 0.0,
      "entry_reason": "No divergence signals detected",
      "timestamp": "2025-10-11T18:09:50.229100",
      "market_condition": "TRENDING_UP",
      "volatility_environment": "High Volatility",
      "position_size": 0.0,
      "stop_loss": 0.0,
      "profit_target": 0.0,
      "auto_approve": true
    },
    "GOOGL": {
      "signal_type": "NO_SIGNAL",
      "confidence": 0.0,
      "entry_reason": "No divergence signals detected",
      "timestamp": "2025-10-11T18:09:50.209222",
      "market_condition": "RANGE_BOUND",
      "volatility_environment": "Medium Volatility",
      "position_size": 0.0,
      "stop_loss": 0.0,
      "profit_target": 0.0,
      "auto_approve": true
    },
    "INTC": {
      "signal_type": "NO_SIGNAL",
      "confidence": 0.0,
      "entry_reason": "No divergence signals detected",
      "timestamp": "2025-10-11T18:09:50.250090",
      "market_condition": "TRENDING_UP",
      "volatility_environment": "High Volatility",
      "position_size": 0.0,
      "stop_loss": 0.0,
      "profit_target": 0.0,
      "auto_approve": true
    }
  },
  "metadata": {
    "strategy_type": "technical_analysis_momentum",
    "signal_types": [
      "STRONG_BUY",
      "BUY",
      "HOLD",
      "NO_SIGNAL"
    ],
    "analysis_method": "rsi_price_divergence_detection",
    "update_frequency": "on_demand",
    "data_source": "schwab_historical_data",
    "optimal_conditions": "oversold_bullish_divergence_or_overbought_bearish_divergence",
    "auto_approve_last_updated": "2025-10-11T18:09:50.279902",
    "auto_approve_status": true
  }
}